api_v1/__init__.py
api_v1/apps.py
api_v1/models.py
api_v1/serializers.py
api_v1/tests.py
api_v1/urls.py
api_v1/views.py
api_v1/migrations/0001_initial.py
api_v1/migrations/__init__.py
myapp/__init__.py
myapp/apps.py
myapp/tests.py
myapp/urls.py
myapp/views.py
mysite/__init__.py
mysite/asgi.py
mysite/settings.py
mysite/urls.py
mysite/wsgi.py
django_rest_swagger_master-1.0.5.dist-info/LICENSE
django_rest_swagger_master-1.0.5.dist-info/METADATA
django_rest_swagger_master-1.0.5.dist-info/WHEEL
django_rest_swagger_master-1.0.5.dist-info/top_level.txt
django_rest_swagger_master-1.0.5.dist-info/RECORD
